README.md
setup.cfg
setup.py
sales_forecast_package/AddArticleInfo.py
sales_forecast_package/SiteCodeSeparator.py
sales_forecast_package/ToSupervised.py
sales_forecast_package/ToSupervisedDiff.py
sales_forecast_package/ToWeeklySalesDataset.py
sales_forecast_package/__init__.py
sales_forecast_package.egg-info/PKG-INFO
sales_forecast_package.egg-info/SOURCES.txt
sales_forecast_package.egg-info/dependency_links.txt
sales_forecast_package.egg-info/not-zip-safe
sales_forecast_package.egg-info/top_level.txt