Metadata-Version: 1.0
Name: sales-forecast-package
Version: 0.0.3
Summary: Preprocessing classes for transforming a time series forecasting problem into a regression problem
Home-page: UNKNOWN
Author: UNKNOWN
Author-email: UNKNOWN
License: UNKNOWN
Platform: UNKNOWN
